MANIFEST.in
README.md
setup.cfg
setup.py
gocamgen/__init__.py
gocamgen/collapsed_assoc.py
gocamgen/errors.py
gocamgen/filter_rule.py
gocamgen/gocamgen.py
gocamgen/gpad_extensions_mapper.py
gocamgen/one_liner.py
gocamgen/rdflib_sparql_wrapper.py
gocamgen/subgraphs.py
gocamgen/triple_pattern_finder.py
gocamgen/utils.py
gocamgen.egg-info/PKG-INFO
gocamgen.egg-info/SOURCES.txt
gocamgen.egg-info/dependency_links.txt
gocamgen.egg-info/requires.txt
gocamgen.egg-info/top_level.txt