Metadata-Version: 2.1
Name: gocamgen
Version: 0.0.5
Summary: Python library for constructing GO-CAM model RDF
Home-page: https://github.com/dustine32/gocamgen
Author: dustine32
Author-email: debert@usc.edu
License: UNKNOWN
Platform: UNKNOWN
